mastery/__init__.py
mastery/calculator.py
pythonmastery_adomas-0.0.6.dist-info/LICENSE
pythonmastery_adomas-0.0.6.dist-info/METADATA
pythonmastery_adomas-0.0.6.dist-info/WHEEL
pythonmastery_adomas-0.0.6.dist-info/top_level.txt
pythonmastery_adomas-0.0.6.dist-info/RECORD
