Metadata-Version: 2.1
Name: pythonmastery-adomas
Version: 0.0.6
Summary: Python Mastery
Author: Adomas Valiukevicius
Author-email: <adomasval08@gmail.com>
License: UNKNOWN
Platform: UNKNOWN
Classifier: Programming Language :: Python :: 3
Classifier: License :: OSI Approved :: MIT License
Classifier: Operating System :: OS Independent
Requires-Python: >=3.6
License-File: LICENSE
